{"list":[{"rank":1,"preRank":-1,"title":"ゆるキャン△ 1","weeklySales":11584,"sales":11584,"releaseDate":"18/3/28","publisher":"FRW","artist":"アニメーション","topRank":1,"times":1,"_id":0},{"rank":2,"preRank":-1,"title":"アイドルマスター SideM 4(完全生産限定版)","weeklySales":8758,"sales":8758,"releaseDate":"18/3/28","publisher":"ANX","artist":"アニメーション","topRank":2,"times":1,"_id":0},{"rank":3,"preRank":-1,"title":"宇宙よりも遠い場所 1","weeklySales":7029,"sales":7029,"releaseDate":"18/3/28","publisher":"KKA","artist":"アニメーション","topRank":3,"times":1,"_id":0},{"rank":4,"preRank":2,"title":"ラブライブ!サンシャイン!! 2nd Season 4【特装限定版】","weeklySales":6188,"sales":34973,"releaseDate":"18/3/23","publisher":"BVS","artist":"アニメーション","topRank":2,"times":2,"_id":0},{"rank":5,"preRank":1,"title":"ガールズ\u0026パンツァー 最終章 第1話","weeklySales":5657,"sales":56931,"releaseDate":"18/3/23","publisher":"BVS","artist":"アニメーション","topRank":1,"times":2,"_id":0},{"rank":6,"preRank":-1,"title":"Fate/Apocrypha Blu-ray Disc BoxII(完全生産限定版)","weeklySales":5263,"sales":5263,"releaseDate":"18/3/28","publisher":"ANX","artist":"アニメーション","topRank":6,"times":1,"_id":0},{"rank":7,"preRank":-1,"title":"ポプテピピック vol.3(Blu-ray)","weeklySales":4289,"sales":4289,"releaseDate":"18/3/28","publisher":"K","artist":"アニメーション","topRank":7,"times":1,"_id":0},{"rank":8,"preRank":-1,"title":"おそ松さん第2期 第4松 BD","weeklySales":4177,"sales":4177,"releaseDate":"18/3/30","publisher":"AVP","artist":"アニメーション","topRank":8,"times":1,"_id":0},{"rank":9,"preRank":-1,"title":"からかい上手の高木さん Vol.1 Blu-ray","weeklySales":3928,"sales":3928,"releaseDate":"18/3/28","publisher":"TOH","artist":"アニメーション","topRank":9,"times":1,"_id":0},{"rank":10,"preRank":3,"title":"アイドリッシュセブン Blu-ray 2【特装限定版】","weeklySales":3123,"sales":13535,"releaseDate":"18/3/23","publisher":"BVS","artist":"アニメーション","topRank":3,"times":2,"_id":0},{"rank":11,"preRank":-1,"title":"新妹魔王の契約者 DEPARTURES Blu-ray","weeklySales":2773,"sales":2773,"releaseDate":"18/3/28","publisher":"KKA","artist":"アニメーション","topRank":11,"times":1,"_id":0},{"rank":12,"preRank":-1,"title":"「りゅうおうのおしごと!」Blu-ray VOL.1(初回限定版)","weeklySales":2394,"sales":2394,"releaseDate":"18/3/28","publisher":"C","artist":"アニメーション","topRank":12,"times":1,"_id":0},{"rank":13,"preRank":-1,"title":"少女終末旅行 3【Blu-ray】","weeklySales":2250,"sales":2250,"releaseDate":"18/3/28","publisher":"KKA","artist":"アニメーション","topRank":13,"times":1,"_id":0},{"rank":14,"preRank":-1,"title":"ブレンド・S 4(完全生産限定版)","weeklySales":1875,"sales":1875,"releaseDate":"18/3/28","publisher":"ANX","artist":"アニメーション","topRank":14,"times":1,"_id":0},{"rank":15,"preRank":-1,"title":"フルメタル・パニック!ディレクターズカット版 第2部:「ワン・ナイト・スタンド」編 Blu-ray","weeklySales":1863,"sales":1863,"releaseDate":"18/3/28","publisher":"KKA","artist":"アニメーション","topRank":15,"times":1,"_id":0},{"rank":16,"preRank":-1,"title":"Just Because! 第4巻\u003c初回限定版\u003e","weeklySales":1658,"sales":1658,"releaseDate":"18/3/28","publisher":"NUE","artist":"アニメーション","topRank":16,"times":1,"_id":0},{"rank":17,"preRank":-1,"title":"スロウスタート 1(完全生産限定版)","weeklySales":1632,"sales":1632,"releaseDate":"18/3/28","publisher":"ANX","artist":"アニメーション","topRank":17,"times":1,"_id":0},{"rank":18,"preRank":-1,"title":"銀魂.ポロリ篇 3(完全生産限定版)","weeklySales":1534,"sales":1534,"releaseDate":"18/3/28","publisher":"ANX","artist":"アニメーション","topRank":18,"times":1,"_id":0},{"rank":19,"preRank":-1,"title":"デスマーチからはじまる異世界狂想曲 1","weeklySales":1507,"sales":1507,"releaseDate":"18/3/30","publisher":"AVP","artist":"アニメーション","topRank":19,"times":1,"_id":0},{"rank":20,"preRank":4,"title":"メアリと魔女の花 ブルーレイ","weeklySales":1337,"sales":7848,"releaseDate":"18/3/20","publisher":"WDS","artist":"アニメーション","topRank":4,"times":2,"_id":0}],"updateTime":1523260800000,"nextUpdateTime":1523260800000,"CNUpdateTime":1523347200000}