{"list":[{"rank":1,"preRank":3,"title":"怪盗グルーのミニオン大脱走 ブルーレイ+DVDセット","weeklySales":7502,"sales":121054,"releaseDate":"17/12/6","publisher":"NUE","artist":"アニメーション","topRank":1,"times":5,"_id":0},{"rank":2,"preRank":5,"title":"ラブライブ!サンシャイン!! 2nd Season 1【特装限定版】","weeklySales":3226,"sales":53299,"releaseDate":"17/12/22","publisher":"BVS","artist":"アニメーション","topRank":1,"times":3,"_id":0},{"rank":3,"preRank":8,"title":"カーズ/クロスロード MovieNEX","weeklySales":3158,"sales":94775,"releaseDate":"17/11/22","publisher":"WDS","artist":"アニメーション","topRank":1,"times":7,"_id":0},{"rank":4,"preRank":-1,"title":"「君の名は。」Blu-ray スタンダード・エディション","weeklySales":1672,"sales":278042,"releaseDate":"17/7/26","publisher":"TOH","artist":"アニメーション","topRank":1,"times":24,"_id":0},{"rank":5,"preRank":13,"title":"モアナと伝説の海 MovieNEX","weeklySales":1403,"sales":210824,"releaseDate":"17/7/5","publisher":"WDS","artist":"アニメーション","topRank":1,"times":27,"_id":0},{"rank":6,"preRank":2,"title":"アイドルマスター SideM 1(完全生産限定版)","weeklySales":972,"sales":14233,"releaseDate":"17/12/27","publisher":"ANX","artist":"アニメーション","topRank":2,"times":2,"_id":0},{"rank":7,"preRank":-1,"title":"天使の3P! 4","weeklySales":947,"sales":947,"releaseDate":"18/1/6","publisher":"HAP/GAG","artist":"アニメーション","topRank":7,"times":1,"_id":0},{"rank":8,"preRank":17,"title":"SING/シング ブルーレイ+DVDセット","weeklySales":887,"sales":117731,"releaseDate":"17/8/2","publisher":"NUE","artist":"アニメーション","topRank":1,"times":23,"_id":0},{"rank":9,"preRank":4,"title":"戦姫絶唱シンフォギアAXZ 4【期間限定版】","weeklySales":842,"sales":9546,"releaseDate":"17/12/27","publisher":"K","artist":"アニメーション","topRank":4,"times":2,"_id":0},{"rank":10,"preRank":1,"title":"終物語 第八巻/おうぎダーク(完全生産限定版)","weeklySales":818,"sales":17061,"releaseDate":"17/12/27","publisher":"ANX","artist":"アニメーション","topRank":1,"times":2,"_id":0},{"rank":11,"preRank":-1,"title":"「君の名は。」Blu-ray スペシャル・エディション","weeklySales":708,"sales":113954,"releaseDate":"17/7/26","publisher":"TOH","artist":"アニメーション","topRank":3,"times":24,"_id":0},{"rank":12,"preRank":19,"title":"BanG Dream!(バンドリ!)Vol.7","weeklySales":666,"sales":7685,"releaseDate":"17/11/22","publisher":"OLP","artist":"アニメーション","topRank":8,"times":7,"_id":0},{"rank":13,"preRank":-1,"title":"アイカツスターズ! 星のツバサシリーズ Blu-ray BOX 2","weeklySales":622,"sales":622,"releaseDate":"18/1/6","publisher":"HAP","artist":"アニメーション","topRank":13,"times":1,"_id":0},{"rank":14,"preRank":-1,"title":"「君の名は。」Blu-ray コレクターズ・エディション 4K Ultra HD Blu-ray同梱(初回生産限定)","weeklySales":563,"sales":143066,"releaseDate":"17/7/26","publisher":"TOH","artist":"アニメーション","topRank":2,"times":23,"_id":0},{"rank":15,"preRank":6,"title":"Fate/Apocrypha Blu-ray Disc BoxI(完全生産限定版)","weeklySales":541,"sales":6725,"releaseDate":"17/12/27","publisher":"ANX","artist":"アニメーション","topRank":6,"times":2,"_id":0},{"rank":16,"preRank":-1,"title":"ズートピア MovieNEX","weeklySales":517,"sales":357921,"releaseDate":"16/8/24","publisher":"WDS","artist":"アニメーション","topRank":1,"times":72,"_id":0},{"rank":17,"preRank":16,"title":"アイドルマスター シンデレラガールズ劇場 2nd SEASON 第2巻","weeklySales":515,"sales":7986,"releaseDate":"17/12/22","publisher":"FTW","artist":"アニメーション","topRank":5,"times":3,"_id":0},{"rank":18,"preRank":-1,"title":"ドラゴンボール超 Blu-ray BOX9","weeklySales":511,"sales":511,"releaseDate":"18/1/6","publisher":"HAP","artist":"アニメーション","topRank":18,"times":1,"_id":0},{"rank":19,"preRank":10,"title":"神撃のバハムート VIRGIN SOUL IV〈初回限定版〉","weeklySales":499,"sales":2689,"releaseDate":"17/12/29","publisher":"NUE","artist":"アニメーション","topRank":10,"times":2,"_id":0},{"rank":20,"preRank":11,"title":"Wake Up,Girls! 新章 vol.1","weeklySales":416,"sales":2407,"releaseDate":"17/12/27","publisher":"DV2","artist":"アニメーション","topRank":11,"times":2,"_id":0}],"updateTime":1516003200000,"nextUpdateTime":1516003200000,"CNUpdateTime":1516089600000}