{"list":[{"rank":1,"sales":-1,"title":"トリプルX:再起動 ブルーレイ+DVDセット","artist":"ヴィン・ディーゼル","releaseDate":"17/7/5","publisher":"NUE","_id":0},{"rank":2,"sales":-1,"title":"アサシン クリード 2枚組ブルーレイ\u0026DVD〔初回生産限定〕","artist":"マイケル・ファスベンダー","releaseDate":"17/7/5","publisher":"FOX","_id":0},{"rank":3,"sales":-1,"title":"シン・ゴジラ Blu-ray","artist":"長谷川博己","releaseDate":"17/3/22","publisher":"TOH","_id":0},{"rank":4,"sales":-1,"title":"【初回仕様】ファンタスティック・ビーストと魔法使いの旅 ブルーレイ\u0026DVDセット","artist":"エディ・レッドメイン","releaseDate":"17/4/19","publisher":"WHV","_id":0},{"rank":5,"sales":-1,"title":"インデペンデンス・デイ:リサージェンス","artist":"ジェフ・ゴールドブラム","releaseDate":"17/7/5","publisher":"FOX","_id":0},{"rank":6,"sales":-1,"title":"ドクター・ストレンジ MovieNEX","artist":"ベネディクト・カンバーバッチ","releaseDate":"17/6/2","publisher":"WDS","_id":0},{"rank":7,"sales":-1,"title":"僕らのごはんは明日で待ってる","artist":"中島裕翔","releaseDate":"17/7/12","publisher":"JST","_id":0},{"rank":8,"sales":-1,"title":"エイリアン H.R.ギーガー・トリビュート・ブルーレイコレクション〔初回生産限定〕","artist":"トム・スケリット","releaseDate":"14/11/5","publisher":"FOX","_id":0},{"rank":9,"sales":-1,"title":"パイレーツ・オブ・カリビアン:ブルーレイ・4ムービー・コレクション","artist":"ジョニー・デップ","releaseDate":"17/6/21","publisher":"WDS","_id":0},{"rank":10,"sales":-1,"title":"デッドプール 2枚組ブルーレイ\u0026DVD〔初回生産限定〕","artist":"ライアン・レイノルズ","releaseDate":"16/10/5","publisher":"FOX","_id":0}],"updateTime":1500026400000,"nextUpdateTime":1500199200000,"CNUpdateTime":1500112800000}