{"list":[{"rank":1,"sales":-1,"title":"ONE OK ROCK 2017 “Ambitions” JAPAN TOUR","artist":"ONE OK ROCK","releaseDate":"18/5/16","publisher":"ASI","_id":0},{"rank":2,"sales":-1,"title":"スター・ウォーズ/最後のジェダイ MovieNEX(初回版)","artist":"マーク・ハミル","releaseDate":"18/4/25","publisher":"WDS","_id":0},{"rank":3,"sales":-1,"title":"HiGH \u0026 LOW THE MOVIE 3/FINAL MISSION","artist":"AKIRA,TAKAHIRO,岩田剛典","releaseDate":"18/5/16","publisher":"RZN","_id":0},{"rank":4,"sales":-1,"title":"劇場版「Fate/stay night[Heaven’s Feel]I.presage flower」(完全生産限定版)","artist":"アニメーション","releaseDate":"18/5/9","publisher":"ANX","_id":0},{"rank":5,"sales":-1,"title":"映画『あさひなぐ』 Blu-ray スペシャル・エディション【完全生産限定版】","artist":"西野七瀬","releaseDate":"18/5/16","publisher":"SL","_id":0},{"rank":6,"sales":-1,"title":"マイティ・ソー バトルロイヤル MovieNEX","artist":"クリス・ヘムズワース","releaseDate":"18/3/7","publisher":"WDS","_id":0},{"rank":7,"sales":-1,"title":"GODZILLA 怪獣惑星 Blu-ray コレクターズ・エディション","artist":"アニメーション","releaseDate":"18/5/16","publisher":"TOH","_id":0},{"rank":8,"sales":-1,"title":"劇場版「Fate/stay night[Heaven’s Feel]I.presage flower」(通常版)","artist":"アニメーション","releaseDate":"18/5/9","publisher":"ANX","_id":0},{"rank":9,"sales":-1,"title":"ワイルド・スピード ICE BREAK","artist":"ヴィン・ディーゼル","releaseDate":"18/5/9","publisher":"NUE","_id":0},{"rank":10,"sales":-1,"title":"SHOGO HAMADA ON THE ROAD 2015-2016“Journey of a Songwriter”","artist":"浜田省吾","releaseDate":"18/4/25","publisher":"SER","_id":0},{"rank":11,"sales":-1,"title":"仮面ライダー平成ジェネレーションズFINAL ビルド\u0026エグゼイドwithレジェンドライダー コレクターズパック","artist":"犬飼貴丈","releaseDate":"18/5/9","publisher":"TOE","_id":0},{"rank":12,"sales":-1,"title":"オリエント急行殺人事件 2枚組ブルーレイ\u0026DVD","artist":"ケネス・ブラナー","releaseDate":"18/5/2","publisher":"FOX","_id":0},{"rank":13,"sales":-1,"title":"鈴村健一 10th Anniversary Live“lo-op”BD","artist":"鈴村健一","releaseDate":"18/5/9","publisher":"LAN","_id":0},{"rank":14,"sales":-1,"title":"GODZILLA 怪獣惑星 Blu-ray スタンダード・エディション","artist":"アニメーション","releaseDate":"18/5/16","publisher":"TOH","_id":0},{"rank":15,"sales":-1,"title":"アウトレイジ 最終章","artist":"ビートたけし","releaseDate":"18/4/24","publisher":"BNT","_id":0},{"rank":16,"sales":-1,"title":"キングスマン:ゴールデン・サークル 2枚組ブルーレイ\u0026DVD","artist":"タロン・エガートン","releaseDate":"18/4/6","publisher":"FOX","_id":0},{"rank":17,"sales":-1,"title":"THE IDOLM@STER SideM GREETING TOUR 2017 ~BEYOND THE DREAM~ LIVE Blu-ray","artist":"アイドルマスターSideM","releaseDate":"18/4/25","publisher":"LAN","_id":0},{"rank":17,"sales":-1,"title":"スパイダーマン:ホームカミング ブルーレイ \u0026 DVDセット","artist":"トム・ホランド","releaseDate":"17/12/20","publisher":"SP","_id":0},{"rank":19,"sales":-1,"title":"舞台『モブサイコ100』 Blu-ray Disc","artist":"伊藤節生","releaseDate":"18/5/16","publisher":"MAV","_id":0},{"rank":19,"sales":-1,"title":"A3! FIRST Blooming FESTIVAL【Blu-ray】","artist":"-","releaseDate":"18/4/25","publisher":"PC","_id":0},{"rank":21,"sales":-1,"title":"美女と野獣 MovieNEX","artist":"エマ・ワトソン","releaseDate":"17/10/4","publisher":"WDS","_id":0},{"rank":22,"sales":-1,"title":"KOBUKURO LIVE TOUR 2017“心”at 広島グリーンアリーナ","artist":"コブクロ","releaseDate":"18/5/16","publisher":"WMJ","_id":0},{"rank":23,"sales":-1,"title":"ガーディアンズ・オブ・ギャラクシー:リミックス MovieNEX","artist":"クリス・プラット","releaseDate":"17/9/6","publisher":"WDS","_id":0},{"rank":24,"sales":-1,"title":"5th YEAR BIRTHDAY LIVE 2017.2.20-22 SAITAMA SUPER ARENA(完全生産限定盤)","artist":"乃木坂46","releaseDate":"18/3/28","publisher":"SR","_id":0},{"rank":25,"sales":-1,"title":"NEWS LIVE TOUR 2017 NEVERLAND","artist":"NEWS","releaseDate":"18/1/24","publisher":"JE","_id":0},{"rank":26,"sales":-1,"title":"Mr.Children DOME \u0026 STADIUM TOUR 2017 Thanksgiving 25","artist":"Mr.Children","releaseDate":"18/3/21","publisher":"TF","_id":0},{"rank":26,"sales":-1,"title":"ガーディアンズ・オブ・ギャラクシー MovieNEX","artist":"クリス・プラット","releaseDate":"15/1/21","publisher":"WDS","_id":0},{"rank":28,"sales":-1,"title":"デッドプール","artist":"ライアン・レイノルズ","releaseDate":"17/6/9","publisher":"FOX","_id":0},{"rank":29,"sales":-1,"title":"Little Glee Monster Arena Tour 2018 -juice !!!!!- at YOKOHAMA ARENA","artist":"Little Glee Monster","releaseDate":"18/5/9","publisher":"SR","_id":0},{"rank":30,"sales":-1,"title":"泥棒役者","artist":"丸山隆平","releaseDate":"18/5/16","publisher":"JST","_id":0}],"updateTime":1526896800000,"nextUpdateTime":1527069600000,"CNUpdateTime":1526983200000}