{"list":[{"rank":1,"preRank":1,"title":"「君の名は。」DVD スタンダード・エディション","weeklySales":15716,"sales":292159,"releaseDate":"17/7/26","publisher":"TOH","artist":"アニメーション","topRank":1,"times":4,"_id":0},{"rank":2,"preRank":2,"title":"ミニオンズ","weeklySales":5442,"sales":124645,"releaseDate":"16/6/3","publisher":"NUE","artist":"アニメーション","topRank":2,"times":64,"_id":0},{"rank":3,"preRank":3,"title":"怪盗グルーの月泥棒(12.04)","weeklySales":5311,"sales":222370,"releaseDate":"12/4/13","publisher":"GUE","artist":"アニメーション","topRank":3,"times":234,"_id":0},{"rank":4,"preRank":4,"title":"怪盗グルーのミニオン危機一発(14.09)","weeklySales":4609,"sales":183724,"releaseDate":"14/9/3","publisher":"NUE","artist":"アニメーション","topRank":3,"times":155,"_id":0},{"rank":5,"preRank":8,"title":"ミニオンズ 9ミニ・ムービー・コレクション","weeklySales":2882,"sales":36889,"releaseDate":"16/11/18","publisher":"NUE","artist":"アニメーション","topRank":5,"times":40,"_id":0},{"rank":6,"preRank":11,"title":"怪盗グルー ミニ・ムービーコレクション 500円 DVD","weeklySales":2727,"sales":125015,"releaseDate":"14/12/19","publisher":"NUE","artist":"アニメーション","topRank":5,"times":140,"_id":0},{"rank":7,"preRank":-1,"title":"「映画 ハイ☆スピード!-Free! Starting Days-」スペシャルイベント 岩鳶中学水泳部 記録会お疲れ様パーティー","weeklySales":2687,"sales":2687,"releaseDate":"17/8/18","publisher":"KYA/ハイスピード製作委員会","artist":"島崎信長","topRank":7,"times":1,"_id":0},{"rank":8,"preRank":9,"title":"ペット","weeklySales":2483,"sales":17586,"releaseDate":"17/7/5","publisher":"NUE","artist":"アニメーション","topRank":5,"times":7,"_id":0},{"rank":9,"preRank":-1,"title":"美男高校地球防衛部LOVE!LOVE!ALL STAR!","weeklySales":2327,"sales":2327,"releaseDate":"17/8/18","publisher":"PC","artist":"-","topRank":9,"times":1,"_id":0},{"rank":10,"preRank":5,"title":"ラ・ラ・ランド DVD スタンダード・エディション","weeklySales":2163,"sales":15903,"releaseDate":"17/8/2","publisher":"GAG","artist":"ライアン・ゴズリング","topRank":3,"times":3,"_id":0},{"rank":11,"preRank":-1,"title":"Mai Kuraki Live Project 2017 “SAWAGE☆LIVE”","weeklySales":2047,"sales":2047,"releaseDate":"17/8/16","publisher":"NTH","artist":"倉木麻衣","topRank":11,"times":1,"_id":0},{"rank":12,"preRank":-1,"title":"行ってみたい!富士総合火力演習","weeklySales":2042,"sales":2042,"releaseDate":"17/8/18","publisher":"LIP","artist":"-","topRank":12,"times":1,"_id":0},{"rank":13,"preRank":-1,"title":"RX-72 vol.13","weeklySales":1810,"sales":1810,"releaseDate":"17/8/16","publisher":"SND","artist":"HISASHI(GLAY)VS 茂木淳一","topRank":13,"times":1,"_id":0},{"rank":14,"preRank":-1,"title":"RX-72 vol.14","weeklySales":1786,"sales":1786,"releaseDate":"17/8/16","publisher":"SND","artist":"HISASHI(GLAY)VS 茂木淳一","topRank":14,"times":1,"_id":0},{"rank":15,"preRank":-1,"title":"L⇔R Doubt tour at NHK hall~last live 1997~","weeklySales":1581,"sales":1581,"releaseDate":"17/8/18","publisher":"PC","artist":"L⇔R","topRank":15,"times":1,"_id":0},{"rank":16,"preRank":10,"title":"映画ドラえもん のび太の南極カチコチ大冒険","weeklySales":1378,"sales":9081,"releaseDate":"17/8/2","publisher":"SGK","artist":"アニメーション","topRank":6,"times":3,"_id":0},{"rank":17,"preRank":22,"title":"「おかあさんといっしょ」メモリアルPlus(プラス)~あしたもきっと だいせいこう~","weeklySales":1369,"sales":62966,"releaseDate":"17/6/7","publisher":"NHE","artist":"横山だいすけ,小野あつこ,三谷たくみ","topRank":1,"times":11,"_id":0},{"rank":18,"preRank":6,"title":"プリズン・ブレイク シーズン5 DVDコレクターズBOX","weeklySales":1327,"sales":4486,"releaseDate":"17/8/11","publisher":"FOX","artist":"ウェントワース・ミラー","topRank":6,"times":2,"_id":0},{"rank":19,"preRank":-1,"title":"「おとうさんといっしょ」ながれぼし","weeklySales":1235,"sales":1235,"releaseDate":"17/8/18","publisher":"NHE","artist":"-","topRank":19,"times":1,"_id":0},{"rank":20,"preRank":-1,"title":"ファイブ DVD-BOX(初回限定版)","weeklySales":1166,"sales":1166,"releaseDate":"17/8/18","publisher":"CX/PC","artist":"佐藤流司","topRank":20,"times":1,"_id":0},{"rank":21,"preRank":29,"title":"デッドプール","weeklySales":1132,"sales":15360,"releaseDate":"17/6/9","publisher":"FOX","artist":"ライアン・レイノルズ","topRank":4,"times":11,"_id":0},{"rank":22,"preRank":27,"title":"インデペンデンス・デイ:リサージェンス","weeklySales":1053,"sales":10296,"releaseDate":"17/7/5","publisher":"FOX","artist":"ジェフ・ゴールドブラム","topRank":9,"times":7,"_id":0},{"rank":23,"preRank":-1,"title":"TVアニメ「進撃の巨人」Season2 Vol.2","weeklySales":990,"sales":990,"releaseDate":"17/8/18","publisher":"PC","artist":"アニメーション","topRank":23,"times":1,"_id":0},{"rank":24,"preRank":30,"title":"スーサイド・スクワッド","weeklySales":975,"sales":12172,"releaseDate":"17/6/14","publisher":"WHV","artist":"ウィル・スミス","topRank":9,"times":10,"_id":0},{"rank":25,"preRank":19,"title":"かぞえてんぐといっしょにかぞえよう!~旅にはかぞえるものがあふれてんぐ~","weeklySales":955,"sales":21192,"releaseDate":"17/7/19","publisher":"NHE","artist":"かぞえてんぐ","topRank":2,"times":5,"_id":0},{"rank":26,"preRank":-1,"title":"LIVE 2017","weeklySales":912,"sales":912,"releaseDate":"17/8/16","publisher":"CDM","artist":"Unlucky Morpheus","topRank":26,"times":1,"_id":0},{"rank":27,"preRank":34,"title":"パイレーツ・オブ・カリビアン/生命の泉 DVD(13.07)","weeklySales":892,"sales":65144,"releaseDate":"13/7/17","publisher":"WDS","artist":"ジョニー・デップ","topRank":4,"times":33,"_id":0},{"rank":28,"preRank":38,"title":"トランスフォーマー/ロストエイジ","weeklySales":872,"sales":51902,"releaseDate":"15/6/10","publisher":"PHE","artist":"マーク・ウォールバーグ","topRank":5,"times":115,"_id":0},{"rank":29,"preRank":17,"title":"ゲームセンターCX PCエンジン スペシャル","weeklySales":850,"sales":12472,"releaseDate":"17/8/2","publisher":"SYJ","artist":"有野晋哉","topRank":4,"times":3,"_id":0},{"rank":30,"preRank":-1,"title":"ゴッドタン マジ歌ライブ2017 マジ武道館","weeklySales":848,"sales":848,"releaseDate":"17/8/16","publisher":"TX","artist":"おぎやはぎ","topRank":30,"times":1,"_id":0},{"rank":31,"preRank":-1,"title":"きょうのキラ君 DVDスペシャル・エディション","weeklySales":809,"sales":809,"releaseDate":"17/8/18","publisher":"AVP","artist":"中川大志","topRank":31,"times":1,"_id":0},{"rank":32,"preRank":35,"title":"ミュータント・ニンジャ・タートルズ:影\u003cシャドウズ\u003e","weeklySales":779,"sales":2555,"releaseDate":"17/8/2","publisher":"NUE","artist":"ミーガン・フォックス","topRank":28,"times":3,"_id":0},{"rank":33,"preRank":31,"title":"となりのトトロ","weeklySales":756,"sales":102597,"releaseDate":"14/7/16","publisher":"WDS","artist":"アニメーション","topRank":15,"times":162,"_id":0},{"rank":34,"preRank":41,"title":"ファンタスティック・ビーストと魔法使いの旅","weeklySales":754,"sales":47424,"releaseDate":"17/4/19","publisher":"WHV","artist":"エディ・レッドメイン","topRank":1,"times":18,"_id":0},{"rank":35,"preRank":33,"title":"ARASHI LIVE TOUR 2016-2017 Are You Happy?","weeklySales":745,"sales":366509,"releaseDate":"17/5/31","publisher":"JST","artist":"嵐","topRank":1,"times":12,"_id":0},{"rank":36,"preRank":37,"title":"JUICE UP!! TOUR FINAL","weeklySales":693,"sales":38740,"releaseDate":"17/6/28","publisher":"WMJ","artist":"WANIMA","topRank":1,"times":8,"_id":0},{"rank":37,"preRank":36,"title":"映画 妖怪ウォッチ 空飛ぶクジラとダブル世界の大冒険だニャン!","weeklySales":674,"sales":17172,"releaseDate":"17/7/5","publisher":"SGK/MFI","artist":"アニメーション","topRank":2,"times":7,"_id":0},{"rank":38,"preRank":40,"title":"Hey!Say!JUMP LIVE TOUR 2016 DEAR.","weeklySales":668,"sales":201120,"releaseDate":"17/4/26","publisher":"JST","artist":"Hey!Say!JUMP","topRank":1,"times":17,"_id":0},{"rank":39,"preRank":-1,"title":"Music Video Tour 2010-2017(DVD)","weeklySales":655,"sales":80975,"releaseDate":"17/5/17","publisher":"V","artist":"星野源","topRank":1,"times":14,"_id":0},{"rank":40,"preRank":43,"title":"ハドソン川の奇跡","weeklySales":646,"sales":2933,"releaseDate":"17/7/26","publisher":"WHV","artist":"トム・ハンクス","topRank":40,"times":4,"_id":0},{"rank":41,"preRank":-1,"title":"REBECCA LIVE ’85-’86 -Maybe Tomorrow \u0026 Secret Gig Complete Edition-","weeklySales":631,"sales":8166,"releaseDate":"17/7/26","publisher":"SND","artist":"レベッカ","topRank":5,"times":4,"_id":0},{"rank":42,"preRank":49,"title":"ワイルド・スピード SKY MISSION","weeklySales":628,"sales":89330,"releaseDate":"16/4/8","publisher":"NUE","artist":"ヴィン・ディーゼル","topRank":4,"times":72,"_id":0},{"rank":43,"preRank":48,"title":"X-MEN:アポカリプス","weeklySales":614,"sales":10428,"releaseDate":"17/6/9","publisher":"FOX","artist":"ジェームズ・マカヴォイ","topRank":5,"times":11,"_id":0},{"rank":44,"preRank":28,"title":"「おかあさんといっしょ」ファミリーコンサート音楽博士のうららかコンサート","weeklySales":594,"sales":5148,"releaseDate":"17/8/2","publisher":"NHE","artist":"花田ゆういちろう,小野あつこ","topRank":7,"times":3,"_id":0},{"rank":45,"preRank":50,"title":"メカニック:ワールドミッション","weeklySales":590,"sales":7932,"releaseDate":"17/6/14","publisher":"WHV","artist":"ジェイソン・ステイサム","topRank":14,"times":10,"_id":0},{"rank":46,"preRank":32,"title":"ジュラシック・ワールド","weeklySales":576,"sales":38677,"releaseDate":"16/10/5","publisher":"NUE","artist":"クリス・プラット","topRank":5,"times":46,"_id":0},{"rank":47,"preRank":-1,"title":"バイオハザード:ザ・ファイナル【初回生産限定】","weeklySales":573,"sales":57110,"releaseDate":"17/3/22","publisher":"SP","artist":"ミラ・ジョヴォヴィッチ","topRank":3,"times":22,"_id":0},{"rank":48,"preRank":44,"title":"「おかあさんといっしょ」最新ソングブック わらうおばけ","weeklySales":545,"sales":34087,"releaseDate":"17/4/19","publisher":"NHE","artist":"横山だいすけ,小野あつこ","topRank":2,"times":18,"_id":0},{"rank":49,"preRank":45,"title":"GENERATIONS LIVE TOUR 2016 SPEEDSTER","weeklySales":511,"sales":78802,"releaseDate":"16/12/28","publisher":"RZN","artist":"GENERATIONS from EXILE TRIBE","topRank":2,"times":34,"_id":0},{"rank":50,"preRank":12,"title":"仮面ライダー×スーパー戦隊 超スーパーヒーロー大戦","weeklySales":509,"sales":2295,"releaseDate":"17/8/9","publisher":"TOE","artist":"飯島寛騎","topRank":12,"times":2,"_id":0}],"updateTime":1503907200000,"nextUpdateTime":1503907200000,"CNUpdateTime":1503993600000}