{"list":[{"rank":1,"sales":33425,"title":"魚図鑑","artist":"サカナクション","releaseDate":"18/3/28","publisher":"V","_id":0},{"rank":2,"sales":23736,"title":"Highway Star","artist":"EXILE THE SECOND","releaseDate":"18/3/28","publisher":"RZN","_id":0},{"rank":3,"sales":11557,"title":"25th L’Anniversary LIVE","artist":"L’Arc-en-Ciel","releaseDate":"18/3/28","publisher":"KS","_id":0},{"rank":4,"sales":0,"title":"Fate/Grand Order Original Soundtrack II","artist":"ゲーム・ミュージック","releaseDate":"18/3/28","publisher":"ANX","_id":0},{"rank":5,"sales":0,"title":"MASSIVE","artist":"B.A.P","releaseDate":"18/3/28","publisher":"K","_id":0},{"rank":6,"sales":0,"title":"ポプテピピック ALL TIME BEST","artist":"TVサントラ","releaseDate":"18/3/28","publisher":"K","_id":0},{"rank":7,"sales":0,"title":"BEST HIT AKG 2(2012-2018)","artist":"ASIAN KUNG-FU GENERATION","releaseDate":"18/3/28","publisher":"KS","_id":0},{"rank":8,"sales":0,"title":"BLACKPINK","artist":"BLACKPINK","releaseDate":"17/8/30","publisher":"YGX","_id":0},{"rank":9,"sales":0,"title":"FUTURE","artist":"Needs","releaseDate":"18/3/28","publisher":"FSB","_id":0},{"rank":10,"sales":0,"title":"ラブライブ!Solo Live! collection Memorial BOX III","artist":"μ’s","releaseDate":"18/3/28","publisher":"LAN","_id":0},{"rank":11,"sales":0,"title":"大逆襲","artist":"あゆみくりかまき","releaseDate":"18/3/28","publisher":"SER","_id":0},{"rank":12,"sales":0,"title":"ダーリン・イン・ザ・フランキス エンディング集 vol.1","artist":"XX:me","releaseDate":"18/3/28","publisher":"ANX","_id":0},{"rank":13,"sales":0,"title":"T.M.R. LIVE REVOLUTION’17 -ROUND HOUSE CUTBACK-","artist":"T.M.Revolution","releaseDate":"18/3/28","publisher":"ES","_id":0},{"rank":14,"sales":0,"title":"BEAT \u0026 ROSES","artist":"及川光博","releaseDate":"18/3/28","publisher":"V","_id":0},{"rank":15,"sales":0,"title":"G.R.N.D.","artist":"GARNiDELiA","releaseDate":"18/3/28","publisher":"SC","_id":0},{"rank":16,"sales":0,"title":"We are CLEAR’S","artist":"CLEAR’S","releaseDate":"18/3/28","publisher":"AVT","_id":0},{"rank":17,"sales":0,"title":"CHATMONCHY Tribute ~My CHATMONCHY~","artist":"オムニバス","releaseDate":"18/3/28","publisher":"KS","_id":0},{"rank":18,"sales":0,"title":"「からかい上手の高木さん」Cover Song Collection","artist":"高木さん(高橋李依)","releaseDate":"18/3/28","publisher":"TOH","_id":0},{"rank":19,"sales":0,"title":"Wake Up,Best!3","artist":"Wake Up,Girls!","releaseDate":"18/3/28","publisher":"DV2","_id":0},{"rank":20,"sales":0,"title":"#compact_disc","artist":"RED SPIDER","releaseDate":"18/3/28","publisher":"V","_id":0},{"rank":21,"sales":0,"title":"THE PREMIUM SYMPHONY","artist":"MY FIRST STORY","releaseDate":"18/3/28","publisher":"ITC","_id":0},{"rank":22,"sales":0,"title":"World Atlas","artist":"fhana","releaseDate":"18/3/28","publisher":"LAN","_id":0},{"rank":23,"sales":0,"title":"BEST HIT AKG Official Bootleg“HONE”","artist":"ASIAN KUNG-FU GENERATION","releaseDate":"18/3/28","publisher":"KS","_id":0},{"rank":24,"sales":0,"title":"BEST HIT AKG Official Bootleg“IMO”","artist":"ASIAN KUNG-FU GENERATION","releaseDate":"18/3/28","publisher":"KS","_id":0},{"rank":25,"sales":0,"title":"ラブライブ!Solo Live! III from μ’s 絢瀬絵里 Memories with Eli","artist":"絢瀬絵里(南條愛乃)","releaseDate":"18/3/28","publisher":"LAN","_id":0},{"rank":26,"sales":0,"title":"CYNICISM","artist":"Neru","releaseDate":"18/3/28","publisher":"NUE","_id":0},{"rank":27,"sales":0,"title":"Driving Hit’s 8","artist":"倖田來未","releaseDate":"18/3/28","publisher":"RZN","_id":0},{"rank":28,"sales":0,"title":"ALL TIME BEST mixed by MIGHTY CROWN","artist":"RIZE","releaseDate":"18/3/28","publisher":"ES","_id":0},{"rank":29,"sales":0,"title":"EPCOTIA","artist":"NEWS","releaseDate":"18/3/21","publisher":"JE","_id":0},{"rank":30,"sales":0,"title":"TVアニメーション「魔法使いの嫁」オリジナルサウンドトラック2","artist":"松本淳一","releaseDate":"18/3/28","publisher":"FLD","_id":0},{"rank":31,"sales":0,"title":"グレイテスト・ショーマン(オリジナル・サウンドトラック)","artist":"Various Artists","releaseDate":"18/1/17","publisher":"WMJ","_id":0},{"rank":32,"sales":0,"title":"TVアニメ『ヴァイオレット・エヴァーガーデン』ボーカルアルバム「Song letters」","artist":"TVサントラ","releaseDate":"18/3/28","publisher":"LAN","_id":0},{"rank":33,"sales":0,"title":"ラブライブ!Solo Live! III from μ’s 園田海未 Memories with Umi","artist":"園田海未(三森すずこ)","releaseDate":"18/3/28","publisher":"LAN","_id":0},{"rank":34,"sales":0,"title":"PLAY","artist":"菅田将暉","releaseDate":"18/3/21","publisher":"ES","_id":0},{"rank":35,"sales":0,"title":"ラブライブ!Solo Live! III from μ’s 南 ことり Memories with Kotori","artist":"南ことり(内田彩)","releaseDate":"18/3/28","publisher":"LAN","_id":0},{"rank":36,"sales":0,"title":"ラブライブ!Solo Live! III from μ’s 西木野真姫 Memories with Maki","artist":"西木野真姫(Pile)","releaseDate":"18/3/28","publisher":"LAN","_id":0},{"rank":37,"sales":0,"title":"BOOTLEG","artist":"米津玄師","releaseDate":"17/11/1","publisher":"SR","_id":0},{"rank":38,"sales":0,"title":"アルバム2","artist":"BULL ZEICHEN 88","releaseDate":"18/3/28","publisher":"TJC","_id":0},{"rank":39,"sales":0,"title":"ラブライブ!Solo Live! III from μ’s 小泉花陽 Memories with Hanayo","artist":"小泉花陽(久保ユリカ)","releaseDate":"18/3/28","publisher":"LAN","_id":0},{"rank":40,"sales":0,"title":"ラブライブ!Solo Live! III from μ’s 高坂穂乃果 Memories with Honoka","artist":"高坂穂乃果(新田恵海)","releaseDate":"18/3/28","publisher":"LAN","_id":0},{"rank":41,"sales":0,"title":"BEST","artist":"三浦大知","releaseDate":"18/3/7","publisher":"SGR","_id":0},{"rank":42,"sales":0,"title":"ラブライブ!Solo Live! III from μ’s 矢澤にこ Memories with Nico","artist":"矢澤にこ(徳井青空)","releaseDate":"18/3/28","publisher":"LAN","_id":0},{"rank":43,"sales":0,"title":"星が降る前に","artist":"JY","releaseDate":"18/3/28","publisher":"SR","_id":0},{"rank":44,"sales":0,"title":"ラブライブ!Solo Live! III from μ’s 星空 凛 Memories with Rin","artist":"星空凛(飯田里穂)","releaseDate":"18/3/28","publisher":"LAN","_id":0},{"rank":45,"sales":0,"title":"ラブライブ!Solo Live! III from μ’s 東條 希 Memories with Nozomi","artist":"東條希(楠田亜衣奈)","releaseDate":"18/3/28","publisher":"LAN","_id":0},{"rank":46,"sales":0,"title":"TVアニメ「宇宙よりも遠い場所」オリジナルサウンドトラック","artist":"藤澤慶昌","releaseDate":"18/3/28","publisher":"KKA","_id":0},{"rank":47,"sales":0,"title":"アニメ『黒子のバスケ』Charactere Song Best Collection","artist":"TVサントラ","releaseDate":"18/3/28","publisher":"LAN","_id":0},{"rank":48,"sales":0,"title":"Finally","artist":"安室奈美恵","releaseDate":"17/11/8","publisher":"DIM","_id":0},{"rank":49,"sales":0,"title":"DIABOLIK LOVERS Para-Selene Vol.12 無神ルキ","artist":"櫻井孝宏","releaseDate":"18/3/28","publisher":"REJ","_id":0},{"rank":50,"sales":0,"title":"ラブとポップ ~好きだった人を思い出す歌がある~ mixed by DJ和","artist":"DJ和","releaseDate":"17/8/9","publisher":"ASR","_id":0}],"updateTime":1522144800000,"nextUpdateTime":1522317600000,"CNUpdateTime":1522231200000}