{"list":[{"rank":1,"sales":-1,"title":"namie amuro LIVE STYLE 2016-2017","artist":"安室奈美恵","releaseDate":"17/5/3","publisher":"DIM","_id":0},{"rank":2,"sales":-1,"title":"武田玲奈 WEEKLY YOUNG JUMP PREMIUM DVD 武田玲奈「rena」","artist":"武田玲奈","releaseDate":"17/9/20","publisher":"LIP","_id":0},{"rank":3,"sales":-1,"title":"この世界の片隅に","artist":"アニメーション","releaseDate":"17/9/15","publisher":"BVS","_id":0},{"rank":4,"sales":-1,"title":"劇場版 ソードアート・オンライン -オーディナル・スケール-(完全生産限定版)","artist":"アニメーション","releaseDate":"17/9/27","publisher":"ANX","_id":0},{"rank":5,"sales":-1,"title":"「君の名は。」DVD スタンダード・エディション","artist":"アニメーション","releaseDate":"17/7/26","publisher":"TOH","_id":0},{"rank":6,"sales":-1,"title":"iKON JAPAN DOME TOUR 2017","artist":"iKON","releaseDate":"17/9/27","publisher":"YGX","_id":0},{"rank":7,"sales":-1,"title":"劇場版 ソードアート・オンライン -オーディナル・スケール-(通常版)","artist":"アニメーション","releaseDate":"17/9/27","publisher":"ANX","_id":0},{"rank":8,"sales":-1,"title":"久松郁実 いくみんのスポコス “I LOVE SPORTS!”","artist":"久松郁実","releaseDate":"17/9/20","publisher":"LIP","_id":0},{"rank":9,"sales":-1,"title":"劇場版 黒子のバスケ LAST GAME\u003c特装限定版\u003e","artist":"アニメーション","releaseDate":"17/9/27","publisher":"BVS","_id":0},{"rank":10,"sales":-1,"title":"赤毛のアン DVDBOX 1","artist":"ミーガン・フォローズ","releaseDate":"17/9/22","publisher":"NHE","_id":0},{"rank":11,"sales":-1,"title":"ミニオンズ 9ミニ・ムービー・コレクション","artist":"アニメーション","releaseDate":"16/11/18","publisher":"NUE","_id":0},{"rank":12,"sales":-1,"title":"天木じゅん #天乳 #1mmでもいいなと思ったら■","artist":"天木じゅん","releaseDate":"17/9/20","publisher":"LIP","_id":0},{"rank":13,"sales":-1,"title":"ミニオンズ","artist":"アニメーション","releaseDate":"16/6/3","publisher":"NUE","_id":0},{"rank":14,"sales":-1,"title":"スター・トレック BEYOND","artist":"クリス・パイン","releaseDate":"17/9/21","publisher":"NUE","_id":0},{"rank":15,"sales":-1,"title":"怪盗グルーのミニオン危機一発(14.09)","artist":"アニメーション","releaseDate":"14/9/3","publisher":"NUE","_id":0},{"rank":16,"sales":-1,"title":"怪盗グルーの月泥棒(12.04)","artist":"アニメーション","releaseDate":"12/4/13","publisher":"GUE","_id":0},{"rank":17,"sales":-1,"title":"miwa ARENA tour 2017“SPLASH☆WORLD”","artist":"miwa","releaseDate":"17/9/27","publisher":"SR","_id":0},{"rank":18,"sales":-1,"title":"namie amuro LIVE STYLE 2014","artist":"安室奈美恵","releaseDate":"15/2/11","publisher":"DIM","_id":0},{"rank":19,"sales":-1,"title":"ペット","artist":"アニメーション","releaseDate":"17/7/5","publisher":"NUE","_id":0},{"rank":20,"sales":-1,"title":"劇場版 黒子のバスケ LAST GAME","artist":"アニメーション","releaseDate":"17/9/27","publisher":"BVS","_id":0}],"updateTime":1506852000000,"nextUpdateTime":1507024800000,"CNUpdateTime":1506938400000}