{"list":[{"rank":1,"preRank":-1,"title":"Live\u0026Documentary「Mr.Children、ヒカリノアトリエで虹の絵を描く」","weeklySales":35495,"sales":35495,"releaseDate":"17/12/20","publisher":"TF","artist":"Mr.Children","topRank":1,"times":1,"_id":0},{"rank":2,"preRank":1,"title":"三代目 J Soul Brothers LIVE TOUR 2016-2017 “METROPOLIZ”","weeklySales":20716,"sales":183764,"releaseDate":"17/12/13","publisher":"RZN","artist":"三代目 J Soul Brothers from EXILE TRIBE","topRank":1,"times":2,"_id":0},{"rank":3,"preRank":-1,"title":"TWICE DEBUT SHOWCASE“Touchdown in JAPAN”","weeklySales":16999,"sales":16999,"releaseDate":"17/12/20","publisher":"WMJ","artist":"TWICE","topRank":3,"times":1,"_id":0},{"rank":4,"preRank":-1,"title":"SummerHolic 2017 -STAR LIGHT- at 横浜 赤レンガ 野外ステージ","weeklySales":8238,"sales":8238,"releaseDate":"17/12/20","publisher":"TF","artist":"湘南乃風","topRank":4,"times":1,"_id":0},{"rank":5,"preRank":-1,"title":"1224 -THE ORIGINAL-","weeklySales":6020,"sales":6020,"releaseDate":"17/12/24","publisher":"UM","artist":"BOΦWY","topRank":5,"times":1,"_id":0},{"rank":6,"preRank":-1,"title":"横浜アリーナ ワンマンライブ 俺ら出会って10年目~shall we dance?~","weeklySales":4833,"sales":4833,"releaseDate":"17/12/20","publisher":"V","artist":"KEYTALK","topRank":6,"times":1,"_id":0},{"rank":7,"preRank":-1,"title":"CLIPS","weeklySales":4711,"sales":4711,"releaseDate":"17/12/20","publisher":"UM","artist":"[Alexandros]","topRank":7,"times":1,"_id":0},{"rank":8,"preRank":-1,"title":"LIVE TOUR 2017遊助祭「星」~あの..星に願いを込めたんですケド。~","weeklySales":3880,"sales":3880,"releaseDate":"17/12/20","publisher":"SR","artist":"遊助","topRank":8,"times":1,"_id":0},{"rank":9,"preRank":-1,"title":"KIM HYUN JOONG JAPAN TOUR 2017“INNER CORE”","weeklySales":2912,"sales":2912,"releaseDate":"17/12/20","publisher":"UM","artist":"キム・ヒョンジュン","topRank":9,"times":1,"_id":0},{"rank":10,"preRank":-1,"title":"PORNOGRAFFITTI 色情塗鴉 Special Live in Taiwan","weeklySales":1896,"sales":1896,"releaseDate":"17/12/20","publisher":"SER","artist":"ポルノグラフィティ","topRank":10,"times":1,"_id":0},{"rank":11,"preRank":-1,"title":"電撃チョモランマ隊25周年記念LIVE DVD「YOUとチョモ~レ~だって、DVDも出せって急かすから■~」","weeklySales":1694,"sales":1694,"releaseDate":"17/12/20","publisher":"PZR","artist":"電撃チョモランマ隊","topRank":11,"times":1,"_id":0},{"rank":12,"preRank":-1,"title":"REBECCA LIVE TOUR 2017 at 日本武道館","weeklySales":1654,"sales":1654,"releaseDate":"17/12/20","publisher":"UM","artist":"REBECCA","topRank":12,"times":1,"_id":0},{"rank":13,"preRank":9,"title":"All Our Yesterdays Tour 2017 at SAITAMA SUPER ARENA","weeklySales":1645,"sales":32599,"releaseDate":"17/11/15","publisher":"UM","artist":"back number","topRank":1,"times":6,"_id":0},{"rank":14,"preRank":11,"title":"namie amuro LIVE STYLE 2016-2017","weeklySales":1390,"sales":119336,"releaseDate":"17/5/3","publisher":"DIM","artist":"安室奈美恵","topRank":1,"times":34,"_id":0},{"rank":15,"preRank":17,"title":"Hey!Say!JUMP LIVE TOUR 2016 DEAR.","weeklySales":1378,"sales":208655,"releaseDate":"17/4/26","publisher":"JST","artist":"Hey!Say!JUMP","topRank":1,"times":35,"_id":0},{"rank":16,"preRank":-1,"title":"LIVE DA PUMP 2016-2017“RED ~ live 20th ~”","weeklySales":1289,"sales":1289,"releaseDate":"17/12/20","publisher":"AVT","artist":"DA PUMP","topRank":16,"times":1,"_id":0},{"rank":17,"preRank":15,"title":"ARASHI LIVE TOUR 2016-2017 Are You Happy?","weeklySales":1246,"sales":376540,"releaseDate":"17/5/31","publisher":"JST","artist":"嵐","topRank":1,"times":30,"_id":0},{"rank":18,"preRank":-1,"title":"lecca LIVE 2017 People on the High Street","weeklySales":1233,"sales":1233,"releaseDate":"17/12/20","publisher":"CUT","artist":"lecca","topRank":18,"times":1,"_id":0},{"rank":19,"preRank":7,"title":"20th Anniversary DOME TOUR 2017「LIVE FILMS ゆずイロハ」","weeklySales":1129,"sales":14510,"releaseDate":"17/12/6","publisher":"SNC","artist":"ゆず","topRank":1,"times":3,"_id":0},{"rank":20,"preRank":-1,"title":"Lead 15th Anniversary LIVE BOX(DVD)","weeklySales":1061,"sales":1061,"releaseDate":"17/12/20","publisher":"PC","artist":"Lead","topRank":20,"times":1,"_id":0},{"rank":21,"preRank":3,"title":"山内惠介コンサート2017~まだ見ぬ歌の巓(いただき)を目指して!~","weeklySales":998,"sales":3816,"releaseDate":"17/12/13","publisher":"V","artist":"山内惠介","topRank":3,"times":2,"_id":0},{"rank":22,"preRank":-1,"title":"Shizuka Kudo 30th Anniversary Live 凛 DVD","weeklySales":994,"sales":994,"releaseDate":"17/12/20","publisher":"PC","artist":"工藤静香","topRank":22,"times":1,"_id":0},{"rank":23,"preRank":-1,"title":"OTODAMA SEA STUDIO 2017 夏だ!海だ!アンジュルムだ!!","weeklySales":873,"sales":873,"releaseDate":"17/12/20","publisher":"UFI","artist":"アンジュルム","topRank":23,"times":1,"_id":0},{"rank":24,"preRank":-1,"title":"Mimori Suzuko Live 2017「Tropical Paradise」","weeklySales":813,"sales":813,"releaseDate":"17/12/20","publisher":"PC","artist":"三森すずこ","topRank":24,"times":1,"_id":0},{"rank":25,"preRank":19,"title":"ジャニーズWEST LIVE TOUR 2017 なうぇすと","weeklySales":812,"sales":51273,"releaseDate":"17/10/25","publisher":"JE","artist":"ジャニーズWEST","topRank":1,"times":9,"_id":0},{"rank":26,"preRank":-1,"title":"HEAVY POSITIVE ROCK FINAL LIVE AT NIPPON BUDOKAN","weeklySales":774,"sales":774,"releaseDate":"17/12/20","publisher":"PC","artist":"SuG","topRank":26,"times":1,"_id":0},{"rank":27,"preRank":21,"title":"Sexy Zone Presents Sexy Tour ~ STAGE(DVD)","weeklySales":740,"sales":49401,"releaseDate":"17/9/6","publisher":"PC","artist":"Sexy Zone","topRank":1,"times":16,"_id":0},{"rank":28,"preRank":13,"title":"Perfume Clips 2","weeklySales":686,"sales":13924,"releaseDate":"17/11/29","publisher":"UM","artist":"Perfume","topRank":2,"times":4,"_id":0},{"rank":29,"preRank":22,"title":"JUICE UP!! TOUR FINAL","weeklySales":685,"sales":44946,"releaseDate":"17/6/28","publisher":"WMJ","artist":"WANIMA","topRank":1,"times":26,"_id":0},{"rank":30,"preRank":10,"title":"KODA KUMI LIVE TOUR 2017 - W FACE -","weeklySales":622,"sales":11338,"releaseDate":"17/12/6","publisher":"RZN","artist":"倖田來未","topRank":2,"times":3,"_id":0}],"updateTime":1514793600000,"nextUpdateTime":1514793600000,"CNUpdateTime":1514880000000}