{"list":[{"rank":1,"preRank":3,"title":"SING/シング","weeklySales":1392,"sales":52044,"releaseDate":"18/3/7","publisher":"NUE","artist":"アニメーション","topRank":1,"times":28,"_id":0},{"rank":2,"preRank":1,"title":"怪盗グルーのミニオン大脱走","weeklySales":1262,"sales":29492,"releaseDate":"18/7/4","publisher":"NUE","artist":"アニメーション","topRank":1,"times":11,"_id":0},{"rank":3,"preRank":-1,"title":"ヲタクに恋は難しい 1(完全生産限定版)","weeklySales":808,"sales":808,"releaseDate":"18/9/12","publisher":"ANX/CX","artist":"アニメーション","topRank":3,"times":1,"_id":0},{"rank":4,"preRank":7,"title":"おしりたんてい1 ププッとかいけつ! おしりたんていとうじょう!","weeklySales":772,"sales":2950,"releaseDate":"18/8/22","publisher":"C","artist":"アニメーション","topRank":4,"times":4,"_id":0},{"rank":5,"preRank":2,"title":"映画ドラえもん のび太の宝島","weeklySales":771,"sales":16013,"releaseDate":"18/8/1","publisher":"SGK","artist":"アニメーション","topRank":1,"times":7,"_id":0},{"rank":6,"preRank":4,"title":"となりのトトロ","weeklySales":605,"sales":133470,"releaseDate":"14/7/16","publisher":"WDS","artist":"アニメーション","topRank":3,"times":218,"_id":0},{"rank":7,"preRank":21,"title":"この世界の片隅に","weeklySales":398,"sales":37996,"releaseDate":"17/9/15","publisher":"BVS","artist":"アニメーション","topRank":1,"times":42,"_id":0},{"rank":8,"preRank":13,"title":"ミニオンズ","weeklySales":372,"sales":182465,"releaseDate":"16/6/3","publisher":"NUE","artist":"アニメーション","topRank":1,"times":120,"_id":0},{"rank":9,"preRank":-1,"title":"世界名作劇場・完結版 家族ロビンソン漂流記 ふしぎな島のフローネ","weeklySales":355,"sales":1113,"releaseDate":"10/1/27","publisher":"BVS","artist":"アニメーション","topRank":9,"times":5,"_id":0},{"rank":10,"preRank":-1,"title":"Fate/EXTRA Last Encore 2(完全生産限定版)","weeklySales":340,"sales":340,"releaseDate":"18/9/12","publisher":"ANX","artist":"アニメーション","topRank":10,"times":1,"_id":0},{"rank":10,"preRank":14,"title":"ペット","weeklySales":340,"sales":55699,"releaseDate":"17/7/5","publisher":"NUE","artist":"アニメーション","topRank":2,"times":63,"_id":0},{"rank":12,"preRank":17,"title":"怪盗グルーの月泥棒(12.04)","weeklySales":298,"sales":274967,"releaseDate":"12/4/13","publisher":"GUE","artist":"アニメーション","topRank":1,"times":290,"_id":0},{"rank":13,"preRank":15,"title":"怪盗グルーのミニオン危機一発(14.09)","weeklySales":275,"sales":233485,"releaseDate":"14/9/3","publisher":"NUE","artist":"アニメーション","topRank":1,"times":211,"_id":0},{"rank":14,"preRank":10,"title":"Mr.インクレディブル(06.06)","weeklySales":245,"sales":62802,"releaseDate":"06/6/16","publisher":"BVH","artist":"アニメーション","topRank":5,"times":82,"_id":0},{"rank":15,"preRank":16,"title":"トイ・ストーリー スペシャル・エディション","weeklySales":243,"sales":225569,"releaseDate":"10/5/21","publisher":"WDS","artist":"アニメーション","topRank":1,"times":203,"_id":0},{"rank":16,"preRank":12,"title":"劇場版 マクロスΔ 激情のワルキューレ【特装限定版】","weeklySales":237,"sales":5595,"releaseDate":"18/8/28","publisher":"BNT","artist":"アニメーション","topRank":2,"times":3,"_id":0},{"rank":17,"preRank":22,"title":"トイ・ストーリー2 スペシャル・エディション","weeklySales":221,"sales":196528,"releaseDate":"10/6/23","publisher":"WDS","artist":"アニメーション","topRank":1,"times":197,"_id":0},{"rank":18,"preRank":9,"title":"はたらく細胞 1(完全生産限定版)","weeklySales":211,"sales":3717,"releaseDate":"18/8/29","publisher":"ANX","artist":"アニメーション","topRank":3,"times":3,"_id":0},{"rank":19,"preRank":11,"title":"アイドリッシュセブン DVD 7【特装限定版】","weeklySales":210,"sales":6381,"releaseDate":"18/8/28","publisher":"BNT","artist":"アニメーション","topRank":1,"times":3,"_id":0},{"rank":20,"preRank":26,"title":"ミニオンズ 9ミニ・ムービー・コレクション","weeklySales":203,"sales":72274,"releaseDate":"16/11/18","publisher":"NUE","artist":"アニメーション","topRank":4,"times":96,"_id":0},{"rank":21,"preRank":22,"title":"魔女の宅急便","weeklySales":181,"sales":57580,"releaseDate":"14/7/16","publisher":"WDS","artist":"アニメーション","topRank":10,"times":215,"_id":0},{"rank":22,"preRank":30,"title":"映画 妖怪ウォッチ シャドウサイド 鬼王の復活","weeklySales":173,"sales":12049,"releaseDate":"18/7/4","publisher":"SGK/MFI","artist":"アニメーション","topRank":1,"times":11,"_id":0},{"rank":23,"preRank":27,"title":"トイ・ストーリー3(12.07)","weeklySales":166,"sales":87272,"releaseDate":"12/7/4","publisher":"WDS","artist":"アニメーション","topRank":1,"times":89,"_id":0},{"rank":24,"preRank":-1,"title":"もののけ姫","weeklySales":153,"sales":22833,"releaseDate":"14/7/16","publisher":"WDS","artist":"アニメーション","topRank":9,"times":122,"_id":0},{"rank":25,"preRank":-1,"title":"千と千尋の神隠し","weeklySales":150,"sales":43716,"releaseDate":"14/7/16","publisher":"WDS","artist":"アニメーション","topRank":9,"times":181,"_id":0},{"rank":26,"preRank":-1,"title":"GRANBLUE FANTASY The Animation 6(完全生産限定版)","weeklySales":133,"sales":30159,"releaseDate":"17/10/25","publisher":"ANX","artist":"アニメーション","topRank":1,"times":47,"_id":0},{"rank":27,"preRank":28,"title":"マジンガーZ/INFINITY 通常版","weeklySales":132,"sales":4739,"releaseDate":"18/8/8","publisher":"KKA","artist":"アニメーション","topRank":1,"times":6,"_id":0},{"rank":27,"preRank":-1,"title":"GRANBLUE FANTASY The Animation 7(完全生産限定版)","weeklySales":132,"sales":33297,"releaseDate":"17/11/29","publisher":"ANX","artist":"アニメーション","topRank":1,"times":42,"_id":0},{"rank":29,"preRank":-1,"title":"カンフー・パンダ3\u003c特別編\u003e","weeklySales":129,"sales":5677,"releaseDate":"18/2/2","publisher":"NUE","artist":"アニメーション","topRank":22,"times":32,"_id":0},{"rank":30,"preRank":18,"title":"ONE PIECE Log Collection“DOFLAMINGO”","weeklySales":127,"sales":6816,"releaseDate":"18/8/24","publisher":"AVP","artist":"アニメーション","topRank":1,"times":4,"_id":0}],"updateTime":1537776000000,"nextUpdateTime":1537776000000,"CNUpdateTime":1537862400000}