{"list":[{"rank":1,"sales":-1,"title":"機動戦士ガンダム THE ORIGIN V 激突 ルウム会戦","artist":"アニメーション","releaseDate":"17/11/10","publisher":"BVS","_id":0},{"rank":2,"sales":-1,"title":"パイレーツ・オブ・カリビアン/最後の海賊 MovieNEX","artist":"ジョニー・デップ","releaseDate":"17/11/8","publisher":"WDS","_id":0},{"rank":3,"sales":-1,"title":"美女と野獣 MovieNEX","artist":"エマ・ワトソン","releaseDate":"17/10/4","publisher":"WDS","_id":0},{"rank":4,"sales":-1,"title":"【初回仕様】無限の住人 ブルーレイ\u0026DVDセット プレミアム・エディション","artist":"木村拓哉","releaseDate":"17/11/8","publisher":"WHV","_id":0},{"rank":5,"sales":-1,"title":"ワイルド・スピード ICE BREAK ブルーレイ+DVDセット","artist":"ヴィン・ディーゼル","releaseDate":"17/10/6","publisher":"NUE","_id":0},{"rank":6,"sales":-1,"title":"SHERLOCK/シャーロック シーズン4 Blu-ray-BOX","artist":"ベネディクト・カンバーバッチ","releaseDate":"17/11/10","publisher":"KKA","_id":0},{"rank":7,"sales":-1,"title":"パイレーツ・オブ・カリビアン/最後の海賊 4K UHD MovieNEX","artist":"ジョニー・デップ","releaseDate":"17/11/8","publisher":"WDS","_id":0},{"rank":8,"sales":-1,"title":"フィフティ・シェイズ・ダーカー コンプリート・バージョン ブルーレイ+DVD+ボーナスDVD セット","artist":"ダコタ・ジョンソン","releaseDate":"17/11/8","publisher":"NUE","_id":0},{"rank":9,"sales":-1,"title":"無限の住人","artist":"木村拓哉","releaseDate":"17/11/8","publisher":"WHV","_id":0},{"rank":10,"sales":-1,"title":"LOGAN/ローガン 2枚組ブルーレイ\u0026DVD","artist":"ヒュー・ジャックマン","releaseDate":"17/10/18","publisher":"FOX","_id":0},{"rank":11,"sales":-1,"title":"ジャック・リーチャー NEVER GO BACK","artist":"トム・クルーズ","releaseDate":"17/11/8","publisher":"NUE","_id":0},{"rank":12,"sales":-1,"title":"映画 クレヨンしんちゃん 襲来!!宇宙人シリリ","artist":"アニメーション","releaseDate":"17/11/10","publisher":"SDO","_id":0},{"rank":13,"sales":-1,"title":"LIVE AT YOKOHAMA STADIUM -10th Anniversary-","artist":"秦 基博","releaseDate":"17/11/8","publisher":"UM","_id":0},{"rank":14,"sales":-1,"title":"賭ケグルイ Blu-ray 2","artist":"アニメーション","releaseDate":"17/11/10","publisher":"FRW","_id":0},{"rank":15,"sales":-1,"title":"ブレードランナー ファイナル・カット 日本語吹替音声追加収録版 ブルーレイ","artist":"ハリソン・フォード","releaseDate":"17/9/20","publisher":"WHV","_id":0},{"rank":16,"sales":-1,"title":"ライヴ・アット・オランピア、パリ","artist":"スティング","releaseDate":"17/11/10","publisher":"UM","_id":0},{"rank":17,"sales":-1,"title":"モアナと伝説の海 MovieNEX","artist":"アニメーション","releaseDate":"17/7/5","publisher":"WDS","_id":0},{"rank":18,"sales":-1,"title":"SING/シング ブルーレイ+DVDセット","artist":"アニメーション","releaseDate":"17/8/2","publisher":"NUE","_id":0},{"rank":19,"sales":-1,"title":"007 スペクター","artist":"ダニエル・クレイグ","releaseDate":"16/12/21","publisher":"FOX","_id":0},{"rank":20,"sales":-1,"title":"ブレードランナー クロニクル","artist":"ハリソン・フォード","releaseDate":"17/9/20","publisher":"WHV","_id":0},{"rank":21,"sales":-1,"title":"劇場版 Free! -Timeless Medley- 絆","artist":"アニメーション","releaseDate":"17/11/1","publisher":"KYA","_id":0},{"rank":22,"sales":-1,"title":"namie amuro LIVE STYLE 2016-2017","artist":"安室奈美恵","releaseDate":"17/5/3","publisher":"DIM","_id":0},{"rank":22,"sales":-1,"title":"デビュー30周年記念コンサート“さらにドーンと行くぜ!”大阪城ホール","artist":"エレファントカシマシ","releaseDate":"17/11/8","publisher":"UM","_id":0},{"rank":24,"sales":-1,"title":"戦姫絶唱シンフォギアAXZ 2【期間限定版】","artist":"アニメーション","releaseDate":"17/10/25","publisher":"K","_id":0},{"rank":25,"sales":-1,"title":"へヴィーオブジェクト Blu-ray BOX","artist":"アニメーション","releaseDate":"17/11/8","publisher":"WHV","_id":0},{"rank":26,"sales":-1,"title":"GRANBLUE FANTASY The Animation 6(完全生産限定版)","artist":"アニメーション","releaseDate":"17/10/25","publisher":"ANX","_id":0},{"rank":26,"sales":-1,"title":"追憶 Blu-ray 豪華版","artist":"岡田准一","releaseDate":"17/11/3","publisher":"TOH","_id":0},{"rank":28,"sales":-1,"title":"ファンタスティック・ビーストと魔法使いの旅","artist":"エディ・レッドメイン","releaseDate":"17/10/18","publisher":"WHV","_id":0},{"rank":29,"sales":-1,"title":"カフェ・ソサエティ ブルーレイ","artist":"ジェシー・アイゼンバーグ","releaseDate":"17/11/10","publisher":"KKA","_id":0},{"rank":29,"sales":-1,"title":"マンチェスター・バイ・ザ・シー ブルーレイ+DVDセット","artist":"ケイシー・アフレック","releaseDate":"17/11/8","publisher":"NUE","_id":0},{"rank":29,"sales":-1,"title":"【期間限定】バットマン vs スーパーマン ジャスティスの誕生 アルティメット・エディション ブルーレイセット","artist":"ベン・アフレック","releaseDate":"17/11/8","publisher":"WHV","_id":0}],"updateTime":1510308000000,"nextUpdateTime":1510480800000,"CNUpdateTime":1510394400000}