{"list":[{"rank":1,"preRank":-1,"title":"NEWS LIVE TOUR 2017 NEVERLAND","weeklySales":60281,"sales":60281,"releaseDate":"18/1/24","publisher":"JE","artist":"NEWS","topRank":1,"times":1,"_id":0},{"rank":2,"preRank":1,"title":"AAA DOME TOUR 2017 -WAY OF GLORY-","weeklySales":6032,"sales":62232,"releaseDate":"18/1/17","publisher":"AVT","artist":"AAA","topRank":1,"times":2,"_id":0},{"rank":3,"preRank":2,"title":"ONE OK ROCK 2016 SPECIAL LIVE IN NAGISAEN","weeklySales":5845,"sales":57898,"releaseDate":"18/1/17","publisher":"ASI","artist":"ONE OK ROCK","topRank":2,"times":2,"_id":0},{"rank":4,"preRank":-1,"title":"神威♂学園 de ヒラキナ祭","weeklySales":3269,"sales":3269,"releaseDate":"18/1/24","publisher":"DET","artist":"GACKT","topRank":4,"times":1,"_id":0},{"rank":5,"preRank":-1,"title":"274ch.プレゼンツ「ふなっしー 絶ブシャー祭り2017~梨祭NASSYI FES.~」","weeklySales":2359,"sales":2359,"releaseDate":"18/1/24","publisher":"FND","artist":"ふなっしー","topRank":5,"times":1,"_id":0},{"rank":6,"preRank":5,"title":"Live Tour“Continues”","weeklySales":2190,"sales":53280,"releaseDate":"18/1/10","publisher":"V","artist":"星野源","topRank":1,"times":3,"_id":0},{"rank":7,"preRank":-1,"title":"Hiromi Go Concert Tour 2017“My Dear...”","weeklySales":2128,"sales":2128,"releaseDate":"18/1/24","publisher":"SR","artist":"郷ひろみ","topRank":7,"times":1,"_id":0},{"rank":8,"preRank":-1,"title":"BIGMAMA in BUDOKAN","weeklySales":1234,"sales":1234,"releaseDate":"18/1/24","publisher":"UKP","artist":"BIGMAMA","topRank":8,"times":1,"_id":0},{"rank":9,"preRank":8,"title":"三代目 J Soul Brothers LIVE TOUR 2016-2017 “METROPOLIZ”","weeklySales":1164,"sales":205407,"releaseDate":"17/12/13","publisher":"RZN","artist":"三代目 J Soul Brothers from EXILE TRIBE","topRank":1,"times":7,"_id":0},{"rank":10,"preRank":10,"title":"2017 BTS LIVE TRILOGY EPISODE III THE WINGS TOUR ~JAPAN EDITION~","weeklySales":1157,"sales":33117,"releaseDate":"17/12/27","publisher":"UM","artist":"BTS (防弾少年団)","topRank":2,"times":5,"_id":0},{"rank":11,"preRank":3,"title":"BIGBANG SPECIAL EVENT 2017","weeklySales":1025,"sales":14119,"releaseDate":"18/1/17","publisher":"YGX","artist":"BIGBANG","topRank":3,"times":2,"_id":0},{"rank":12,"preRank":12,"title":"E-girls LIVE 2017 ~E.G.EVOLUTION~","weeklySales":949,"sales":44963,"releaseDate":"17/12/28","publisher":"RZN","artist":"E-girls","topRank":1,"times":5,"_id":0},{"rank":13,"preRank":11,"title":"TWICE DEBUT SHOWCASE“Touchdown in JAPAN”","weeklySales":944,"sales":28139,"releaseDate":"17/12/20","publisher":"WMJ","artist":"TWICE","topRank":3,"times":6,"_id":0},{"rank":14,"preRank":7,"title":"MVP","weeklySales":868,"sales":40983,"releaseDate":"18/1/3","publisher":"V","artist":"桑田佳祐","topRank":1,"times":4,"_id":0},{"rank":15,"preRank":-1,"title":"Apink 3rd LIVE TOUR 2017“3years”at Pacifico Yokohama","weeklySales":813,"sales":813,"releaseDate":"18/1/24","publisher":"UM","artist":"Apink","topRank":15,"times":1,"_id":0},{"rank":16,"preRank":-1,"title":"B-PROJECT on STAGE『OVER the WAVE!』【LIVE】","weeklySales":765,"sales":765,"releaseDate":"18/1/24","publisher":"MAV","artist":"B-PROJECT","topRank":16,"times":1,"_id":0},{"rank":17,"preRank":15,"title":"清水翔太 LIVE TOUR 2017“FLY”","weeklySales":712,"sales":5557,"releaseDate":"18/1/10","publisher":"SR","artist":"清水翔太","topRank":2,"times":3,"_id":0},{"rank":18,"preRank":13,"title":"JUICE UP!! TOUR FINAL","weeklySales":661,"sales":48560,"releaseDate":"17/6/28","publisher":"WMJ","artist":"WANIMA","topRank":1,"times":31,"_id":0},{"rank":19,"preRank":14,"title":"namie amuro LIVE STYLE 2016-2017","weeklySales":633,"sales":125435,"releaseDate":"17/5/3","publisher":"DIM","artist":"安室奈美恵","topRank":1,"times":39,"_id":0},{"rank":20,"preRank":-1,"title":"U-KISS LIVE EVENT 2017 ~Stay with U~","weeklySales":600,"sales":600,"releaseDate":"18/1/24","publisher":"AVT","artist":"U-KISS","topRank":20,"times":1,"_id":0},{"rank":21,"preRank":19,"title":"Live Chronicle 2005-2017","weeklySales":528,"sales":10586,"releaseDate":"17/12/27","publisher":"SGR","artist":"三浦大知","topRank":5,"times":5,"_id":0},{"rank":22,"preRank":4,"title":"ももクロ夏のバカ騒ぎ2017‐FIVE THE COLOR Road to 2020‐味の素スタジアム大会 LIVE DVD","weeklySales":493,"sales":5192,"releaseDate":"18/1/17","publisher":"K","artist":"ももいろクローバーZ","topRank":4,"times":2,"_id":0},{"rank":23,"preRank":17,"title":"Live\u0026Documentary「Mr.Children、ヒカリノアトリエで虹の絵を描く」","weeklySales":468,"sales":43284,"releaseDate":"17/12/20","publisher":"TF","artist":"Mr.Children","topRank":1,"times":6,"_id":0},{"rank":24,"preRank":24,"title":"Hey!Say!JUMP LIVE TOUR 2016 DEAR.","weeklySales":398,"sales":211690,"releaseDate":"17/4/26","publisher":"JST","artist":"Hey!Say!JUMP","topRank":1,"times":40,"_id":0},{"rank":25,"preRank":23,"title":"ARASHI LIVE TOUR 2016-2017 Are You Happy?","weeklySales":388,"sales":379451,"releaseDate":"17/5/31","publisher":"JST","artist":"嵐","topRank":1,"times":35,"_id":0},{"rank":26,"preRank":-1,"title":"極悪祭2017","weeklySales":337,"sales":337,"releaseDate":"18/1/24","publisher":"UM","artist":"アウトレイジ","topRank":26,"times":1,"_id":0},{"rank":27,"preRank":25,"title":"Sexy Zone Presents Sexy Tour ~ STAGE(DVD)","weeklySales":316,"sales":51468,"releaseDate":"17/9/6","publisher":"PC","artist":"Sexy Zone","topRank":1,"times":21,"_id":0},{"rank":28,"preRank":27,"title":"Hey!Say!JUMP LIVE TOUR 2015 JUMPing CARnival","weeklySales":310,"sales":222558,"releaseDate":"16/2/10","publisher":"JST","artist":"Hey!Say!JUMP","topRank":1,"times":100,"_id":0},{"rank":29,"preRank":9,"title":"“Utopia”tour 2017","weeklySales":294,"sales":2116,"releaseDate":"18/1/17","publisher":"SR","artist":"加藤ミリヤ","topRank":9,"times":2,"_id":0},{"rank":30,"preRank":28,"title":"ジャニーズWEST LIVE TOUR 2017 なうぇすと","weeklySales":281,"sales":53670,"releaseDate":"17/10/25","publisher":"JE","artist":"ジャニーズWEST","topRank":1,"times":14,"_id":0}],"updateTime":1517817600000,"nextUpdateTime":1517817600000,"CNUpdateTime":1517904000000}