{"list":[{"rank":1,"preRank":-1,"title":"ハン・ソロ/スター・ウォーズ・ストーリー MovieNEX(初回版)","weeklySales":47539,"sales":47539,"releaseDate":"18/10/17","publisher":"WDS","artist":"オールデン・エアエンライク","topRank":1,"times":1,"_id":0},{"rank":2,"preRank":-1,"title":"ハン・ソロ/スター・ウォーズ・ストーリー 4K UHD MovieNEX","weeklySales":5117,"sales":5117,"releaseDate":"18/10/17","publisher":"WDS","artist":"オールデン・エアエンライク","topRank":2,"times":1,"_id":0},{"rank":3,"preRank":1,"title":"パシフィック・リム:アップライジング ブルーレイ+DVDセット","weeklySales":3714,"sales":17344,"releaseDate":"18/10/11","publisher":"NUE","artist":"ジョン・ボイエガ","topRank":1,"times":2,"_id":0},{"rank":4,"preRank":-1,"title":"ハン・ソロ/スター・ウォーズ・ストーリー 4K UHD MovieNEX スチールブック(数量限定)","weeklySales":3209,"sales":3209,"releaseDate":"18/10/17","publisher":"WDS","artist":"オールデン・エアエンライク","topRank":4,"times":1,"_id":0},{"rank":5,"preRank":-1,"title":"ハン・ソロ/スター・ウォーズ・ストーリー MovieNEX","weeklySales":3020,"sales":3020,"releaseDate":"18/10/17","publisher":"WDS","artist":"オールデン・エアエンライク","topRank":5,"times":1,"_id":0},{"rank":6,"preRank":-1,"title":"酔拳2 HDデジタル・リマスター ブルーレイ アルティメット・コレクターズ・エディション","weeklySales":2290,"sales":2290,"releaseDate":"18/10/19","publisher":"WHV","artist":"ジャッキー・チェン","topRank":6,"times":1,"_id":0},{"rank":7,"preRank":-1,"title":"キングスマン:ゴールデン・サークル","weeklySales":1358,"sales":1358,"releaseDate":"18/10/17","publisher":"FOX","artist":"タロン・エガートン","topRank":7,"times":1,"_id":0},{"rank":8,"preRank":7,"title":"アベンジャーズ/インフィニティ・ウォー MovieNEX","weeklySales":1155,"sales":102909,"releaseDate":"18/9/5","publisher":"WDS","artist":"ロバート・ダウニーJr.","topRank":1,"times":7,"_id":0},{"rank":9,"preRank":2,"title":"ピーターラビット ブルーレイ\u0026DVDセット【初回生産限定】","weeklySales":1048,"sales":8255,"releaseDate":"18/10/10","publisher":"SP","artist":"ローズ・バーン","topRank":2,"times":2,"_id":0},{"rank":10,"preRank":9,"title":"デッドプール2 3枚組ブルーレイ\u0026DVD","weeklySales":950,"sales":43821,"releaseDate":"18/9/12","publisher":"FOX","artist":"ライアン・レイノルズ","topRank":1,"times":6,"_id":0}],"updateTime":1540800000000,"nextUpdateTime":1540800000000,"CNUpdateTime":1540886400000}