{"list":[{"rank":1,"sales":7981,"title":"ユーミンからの、恋のうた。","artist":"松任谷由実","releaseDate":"18/4/11","publisher":"UM","_id":0},{"rank":2,"sales":1727,"title":"うれD","artist":"GReeeeN","releaseDate":"18/4/11","publisher":"UM","_id":0},{"rank":3,"sales":1144,"title":"FACE YOURSELF","artist":"BTS (防弾少年団)","releaseDate":"18/4/4","publisher":"UM","_id":0},{"rank":4,"sales":0,"title":"BIG YELL","artist":"ゆず","releaseDate":"18/4/4","publisher":"SNC","_id":0},{"rank":5,"sales":0,"title":"IV","artist":"5tion","releaseDate":"18/4/11","publisher":"MUU","_id":0},{"rank":6,"sales":0,"title":"松任谷由実 40周年記念ベストアルバム 日本の恋と、ユーミンと。","artist":"松任谷由実","releaseDate":"12/11/20","publisher":"TO","_id":0},{"rank":7,"sales":0,"title":"グレイテスト・ショーマン(オリジナル・サウンドトラック)","artist":"Various Artists","releaseDate":"18/1/17","publisher":"WMJ","_id":0},{"rank":8,"sales":0,"title":"魚図鑑","artist":"サカナクション","releaseDate":"18/3/28","publisher":"V","_id":0},{"rank":9,"sales":0,"title":"機動戦士ガンダム00 10th ANNIVERSARY BEST","artist":"Various Artists","releaseDate":"18/4/11","publisher":"SC","_id":0},{"rank":10,"sales":0,"title":"PLANET BONDS","artist":"FTISLAND","releaseDate":"18/4/11","publisher":"WMJ","_id":0},{"rank":11,"sales":0,"title":"Trignal 5周年企画ミニアルバム「tricolore」","artist":"Trignal","releaseDate":"18/4/11","publisher":"LAN","_id":0},{"rank":12,"sales":0,"title":"PTXプレゼンツ:トップ・ポップ VOL.I(ジャパン・エディション)","artist":"ペンタトニックス","releaseDate":"18/4/13","publisher":"SJI","_id":0},{"rank":13,"sales":0,"title":"Hi-Fi POPS","artist":"ORESAMA","releaseDate":"18/4/11","publisher":"LAN","_id":0},{"rank":14,"sales":0,"title":"ときおとめ","artist":"ときめき■宣伝部","releaseDate":"18/4/11","publisher":"UM","_id":0},{"rank":15,"sales":0,"title":"Finally","artist":"安室奈美恵","releaseDate":"17/11/8","publisher":"DIM","_id":0},{"rank":16,"sales":0,"title":"BOOTLEG","artist":"米津玄師","releaseDate":"17/11/1","publisher":"SR","_id":0},{"rank":17,"sales":0,"title":"ラブとポップ ~好きだった人を思い出す歌がある~ mixed by DJ和","artist":"DJ和","releaseDate":"17/8/9","publisher":"ASR","_id":0},{"rank":18,"sales":0,"title":"「からかい上手の高木さん」Cover Song Collection","artist":"高木さん(高橋李依)","releaseDate":"18/3/28","publisher":"TOH","_id":0},{"rank":19,"sales":0,"title":"THE EMPiRE STRiKES START!!","artist":"EMPiRE","releaseDate":"18/4/11","publisher":"AVT","_id":0},{"rank":20,"sales":0,"title":"クリープ・ショー","artist":"Creepy Nuts","releaseDate":"18/4/11","publisher":"SME","_id":0},{"rank":20,"sales":0,"title":"GOOD LUCK TRACK","artist":"竹原ピストル","releaseDate":"18/4/4","publisher":"V","_id":0},{"rank":22,"sales":0,"title":"メタル・ガレージ(リマスター)","artist":"メタリカ","releaseDate":"18/4/13","publisher":"UM","_id":0},{"rank":23,"sales":0,"title":"24K・マジック(デラックス・エディション)","artist":"ブルーノ・マーズ","releaseDate":"18/4/11","publisher":"WMJ","_id":0},{"rank":24,"sales":0,"title":"BEST","artist":"三浦大知","releaseDate":"18/3/7","publisher":"SGR","_id":0},{"rank":25,"sales":0,"title":"Flight","artist":"Goose house","releaseDate":"18/4/11","publisher":"SR","_id":0},{"rank":26,"sales":0,"title":"STAY ALIVE","artist":"brainchild’s","releaseDate":"18/4/11","publisher":"AOJ","_id":0},{"rank":26,"sales":0,"title":"エスカパレード","artist":"Official髭男dism","releaseDate":"18/4/11","publisher":"LRM","_id":0},{"rank":28,"sales":0,"title":"Fate/Grand Order Original Soundtrack II","artist":"サウンドトラック","releaseDate":"18/3/28","publisher":"ANX","_id":0},{"rank":29,"sales":0,"title":"Persona4 the ANIMATION Series Original Soundtrack","artist":"サウンドトラック","releaseDate":"18/4/11","publisher":"ANX","_id":0},{"rank":30,"sales":0,"title":"週刊少年ジャンプ50th Anniversary BEST ANIME MIX vol.2","artist":"Various Artists","releaseDate":"18/4/4","publisher":"ES","_id":0},{"rank":31,"sales":0,"title":"リメンバー・ミー オリジナル・サウンドトラック","artist":"Various Artists","releaseDate":"18/3/14","publisher":"WDJ","_id":0},{"rank":32,"sales":0,"title":"EPCOTIA","artist":"NEWS","releaseDate":"18/3/21","publisher":"JE","_id":0},{"rank":33,"sales":0,"title":"TVアニメ「ゆるキャン△」オリジナル・サウンドトラック","artist":"立山秋航","releaseDate":"18/3/21","publisher":"5PB","_id":0},{"rank":34,"sales":0,"title":"PLAY","artist":"菅田将暉","releaseDate":"18/3/21","publisher":"ES","_id":0},{"rank":35,"sales":0,"title":"Highway Star","artist":"EXILE THE SECOND","releaseDate":"18/3/28","publisher":"RZN","_id":0},{"rank":36,"sales":0,"title":"劇場版 名探偵コナン『ゼロの執行人』オリジナル・サウンドトラック","artist":"大野克夫","releaseDate":"18/4/11","publisher":"BG","_id":0},{"rank":36,"sales":0,"title":"押忍!番長~操 BEST COLLECTION~","artist":"Daito Music","releaseDate":"18/4/4","publisher":"DAT","_id":0},{"rank":38,"sales":0,"title":"THE IDOLM@STER MILLION LIVE! M@STER SPARKLE 08","artist":"北上麗花(平山笑美),島原エレナ(角元明日香),田中琴葉(種田梨沙),天空橋朋花(小岩井ことり)","releaseDate":"18/4/4","publisher":"LAN","_id":0},{"rank":39,"sales":0,"title":"GET DOWN THE MACKSHOW","artist":"THE MACKSHOW","releaseDate":"18/4/11","publisher":"BAD","_id":0},{"rank":40,"sales":0,"title":"ダーリン・イン・ザ・フランキス エンディング集 vol.1","artist":"XX:me","releaseDate":"18/3/28","publisher":"ANX","_id":0},{"rank":40,"sales":0,"title":"I","artist":"JUJU","releaseDate":"18/2/21","publisher":"ASR","_id":0},{"rank":42,"sales":0,"title":"Everybody!!","artist":"WANIMA","releaseDate":"18/1/17","publisher":"WMJ","_id":0},{"rank":43,"sales":0,"title":"SID Anime Best 2008-2017","artist":"シド","releaseDate":"18/4/4","publisher":"KS","_id":0},{"rank":44,"sales":0,"title":"ポプテピピック ALL TIME BEST","artist":"吟(BUSTED ROSE)","releaseDate":"18/3/28","publisher":"K","_id":0},{"rank":45,"sales":0,"title":"真っ白なものは汚したくなる","artist":"欅坂46","releaseDate":"17/7/19","publisher":"SR","_id":0},{"rank":45,"sales":0,"title":"YANKEE","artist":"米津玄師","releaseDate":"14/4/23","publisher":"UM","_id":0},{"rank":47,"sales":0,"title":"BEST HIT AKG 2(2012-2018)","artist":"ASIAN KUNG-FU GENERATION","releaseDate":"18/3/28","publisher":"KS","_id":0},{"rank":48,"sales":0,"title":"÷(ディバイド)","artist":"エド・シーラン","releaseDate":"17/3/3","publisher":"WMJ","_id":0},{"rank":49,"sales":0,"title":"CHATMONCHY Tribute ~My CHATMONCHY~","artist":"Various Artists","releaseDate":"18/3/28","publisher":"KS","_id":0},{"rank":50,"sales":0,"title":"G.R.N.D.","artist":"GARNiDELiA","releaseDate":"18/3/28","publisher":"SC","_id":0}],"updateTime":1523613600000,"nextUpdateTime":1523786400000,"CNUpdateTime":1523700000000}