{"list":[{"rank":1,"sales":-1,"title":"ハン・ソロ/スター・ウォーズ・ストーリー MovieNEX(初回版)","artist":"オールデン・エアエンライク","releaseDate":"18/10/17","publisher":"WDS","_id":0},{"rank":2,"sales":-1,"title":"ハン・ソロ/スター・ウォーズ・ストーリー 4K UHD MovieNEX","artist":"オールデン・エアエンライク","releaseDate":"18/10/17","publisher":"WDS","_id":0},{"rank":3,"sales":-1,"title":"ハン・ソロ/スター・ウォーズ・ストーリー 4K UHD MovieNEX スチールブック(数量限定)","artist":"オールデン・エアエンライク","releaseDate":"18/10/17","publisher":"WDS","_id":0},{"rank":4,"sales":-1,"title":"ハン・ソロ/スター・ウォーズ・ストーリー MovieNEX","artist":"オールデン・エアエンライク","releaseDate":"18/10/17","publisher":"WDS","_id":0},{"rank":5,"sales":-1,"title":"パシフィック・リム:アップライジング ブルーレイ+DVDセット","artist":"ジョン・ボイエガ","releaseDate":"18/10/11","publisher":"NUE","_id":0},{"rank":6,"sales":-1,"title":"レザーフェイス-悪魔のいけにえ","artist":"スティーヴン・ドーフ","releaseDate":"18/10/17","publisher":"SHV","_id":0},{"rank":7,"sales":-1,"title":"キングスマン:ゴールデン・サークル","artist":"タロン・エガートン","releaseDate":"18/10/17","publisher":"FOX","_id":0},{"rank":8,"sales":-1,"title":"狼よさらば","artist":"チャールズ・ブロンソン","releaseDate":"18/10/17","publisher":"SP","_id":0},{"rank":9,"sales":-1,"title":"ピーターラビット ブルーレイ\u0026DVDセット【初回生産限定】","artist":"ローズ・バーン","releaseDate":"18/10/10","publisher":"SP","_id":0},{"rank":10,"sales":-1,"title":"フューチャーワールド ブルーレイ\u0026DVDセット","artist":"ジェームズ・フランコ","releaseDate":"18/10/17","publisher":"WHV","_id":0}],"updateTime":1539684000000,"nextUpdateTime":1539856800000,"CNUpdateTime":1539770400000}